README.rst
setup.cfg
setup.py
accessor/__init__.py
accessor/accessors.py
accessor/exceptions.py
accessor/utils.py
accessor.egg-info/PKG-INFO
accessor.egg-info/SOURCES.txt
accessor.egg-info/dependency_links.txt
accessor.egg-info/top_level.txt