Metadata-Version: 1.1
Name: accessor
Version: 0.1
Summary: A simple python module for resolving paths on python objects
Home-page: http://github.com/schwobaseggl/accessor
Author: Veit Rückert
Author-email: veit.rueckert@web.de
License: UNKNOWN
Download-URL: http://github.com/schwobaseggl/accessor/archive/0.1.tar.gz
Keywords: accessor attribute key index resolve
Platform: UNKNOWN
Classifier: Development Status :: 2 - Pre-Alpha
Classifier: Framework :: Django
Classifier: Environment :: Plugins
Classifier: Intended Audience :: Developers
Classifier: Operating System :: OS Independent
Classifier: Programming Language :: Python
Classifier: Programming Language :: Python :: 2
Classifier: Programming Language :: Python :: 2.7
Classifier: Programming Language :: Python :: 3
Classifier: Programming Language :: Python :: 3.4
Classifier: Programming Language :: Python :: 3.5
Classifier: Topic :: Software Development :: Libraries :: Python Modules
Classifier: License :: OSI Approved :: MIT License
